setup.py
jznet.egg-info/PKG-INFO
jznet.egg-info/SOURCES.txt
jznet.egg-info/dependency_links.txt
jznet.egg-info/top_level.txt
pyjznet/__init__.py
pyjznet/core_services.py
pyjznet/decorators.py
pyjznet/id_helper.py
pyjznet/listeners.py
pyjznet/messages.py
pyjznet/pools.py
pyjznet/processors.py
pyjznet/server.py
pyjznet/services.py
pyjznet/threadpool.py
pyjznet/utils.py
pyzjnettest/__init__.py
pyzjnettest/testserver.py