Metadata-Version: 1.0
Name: jznet
Version: 0.0.2-alpha2
Summary: a python RPC library based on websocket
Home-page: UNKNOWN
Author: zoowii
Author-email: 1992zhouwei@gmail.com
License: MIT License
Keywords: net,websocket,RPC
Platform: any
